Metadata-Version: 2.1
Name: werfklas
Version: 0.0.7
Home-page: 
Author: Yves van Elk
Author-email: 
Requires-Dist: chardet (==5.0.0)
Requires-Dist: Click (==8.1.3)
Requires-Dist: dominate (==2.7.0)
Requires-Dist: Flask (==2.2.2)
Requires-Dist: Flask-Bootstrap4 (==4.0.2)
Requires-Dist: Flask-SQLAlchemy (==2.5.1)
Requires-Dist: itsdangerous (==2.1.2)
Requires-Dist: Jinja2 (==3.1.2)
Requires-Dist: MarkupSafe (==2.1.1)
Requires-Dist: requests (==2.28.1)
Requires-Dist: SQLAlchemy (==1.4.41)
Requires-Dist: urllib3 (==1.26.12)
Requires-Dist: visitor (==0.1.3)
Requires-Dist: Werkzeug (==2.2.2)
Requires-Dist: Flask-WTF (==1.0.1)
Requires-Dist: WTForms (==2.2.1)
Requires-Dist: python-dateutil
Requires-Dist: flask-assets
Requires-Dist: PyYAML (~=6.0)
Requires-Dist: pathlib
Requires-Dist: waitress (~=2.1.2)
